{
  "name": "CFML DogAPI",
  "version": "1.0.0",
  "author":"Matthew Clemente <mjclemente@gmail.com>",
  "location": "mjclemente/cfmldogapi#v1.0.0",
  "homepage": "https://github.com/mjclemente/cfmldogapi",
  "repository": {
    "type": "git",
    "URL": "https://github.com/mjclemente/cfmldogapi"
  },
  "bugs":"https://github.com/mjclemente/cfmldogapi/issues",
  "slug": "cfmldogapi",
  "changelog":"",
  "contributors":[],
  "dependencies":{},
  "description":"",
  "devDependencies":{},
  "documentation":"",
  "installPaths":{},
  "instructions":"",
  "keywords":[ "dogs", "api", "images", "dog.ceo" ],
  "license":[
    {
      "type": "MIT",
      "URL": "https://github.com/mjclemente/cfmldogapi/blob/master/LICENSE"
    }
  ],
  "private":false,
  "projectURL":"",
  "scripts":{},
  "shortDescription":"A CFML wrapper for The Dog API. Interact with the self-proclaimed largest open source collection of dog pictures on the internet.",
  "ignore": [
    "**/.*",
    "/test/",
    "/tests/"
  ],
  "testbox":{
      "bundles":"",
      "directory":"tests.specs",
      "labels":"",
      "options":{},
      "recurse":true,
      "reporter":"",
      "runner":[
          {
              "default":""
          }
      ],
      "testBundles":"",
      "testSpecs":"",
      "testSuites":"",
      "verbose":true,
      "watchDelay":500,
      "watchPaths":"**.cfc"
  },
  "type":"modules"
}
